argeye/__init__.py
argeye/argeye.py
argeye-0.0.3.dist-info/LICENSE.txt
argeye-0.0.3.dist-info/METADATA
argeye-0.0.3.dist-info/WHEEL
argeye-0.0.3.dist-info/top_level.txt
argeye-0.0.3.dist-info/RECORD
