Metadata-Version: 2.1
Name: argeye
Version: 0.0.3
Summary: A small optimization of Python library argparse.All original usage are retained,but adding a yml file so the user can set the arguments by editing the yml file.
Home-page: https://github.com/llzmgjzhy/argeye.git
Author: llzmgjzhy
Author-email: bmnjklipo@qq.com
Classifier: Programming Language :: Python :: 3
Classifier: License :: OSI Approved :: MIT License
Classifier: Operating System :: OS Independent
Requires-Python: >=3.6
License-File: LICENSE.txt
